SmartAi/__init__.py
SmartAi/core.py
sharvin808_smartai_tools-1.0.0.dist-info/METADATA
sharvin808_smartai_tools-1.0.0.dist-info/WHEEL
sharvin808_smartai_tools-1.0.0.dist-info/top_level.txt
sharvin808_smartai_tools-1.0.0.dist-info/RECORD
