Metadata-Version: 2.4
Name: sharvin808_smartai_tools
Version: 1.0.0
Summary: A simple AI helper library with custom response and summarization functions.
Author: Sharvin Vincent
License: MIT
Requires-Python: >=3.7
